{
  "items": [
    {
      "id": 1,
      "name": "item1",
      "description": "description1",
      "image": "https://via.placeholder.com/150"
    },
    {
      "id": 2,
      "name": "item2",
      "description": "description2",
      "image": "https://via.placeholder.com/150"
    },
    {
      "id": 3,
      "name": "item3",
      "description": "description3",
      "image": "https://via.placeholder.com/150"
    },
    {
      "id": 4,
      "name": "item4",
      "description": "description4",
      "image": "https://via.placeholder.com/150"
    },
    {
      "id": 5,
      "name": "item5",
      "description": "description5",
      "image": "https://via.placeholder.com/150"
    },
    {
      "id": 6,
      "name": "item6",
      "description": "description6",
      "image": "https://via.placeholder.com/150"
    },
    {
      "id": 7,
      "name": "item7",
      "description": "description7",
      "image": "https://via.placeholder.com/150"
    },
    {
      "id": 8,
      "name": "item8",
      "description": "description8",
      "image": "https://via.placeholder.com/150"
    },
    {
      "id": 9,
      "name": "item9",
      "description": "description9",
      "image": "https://via.placeholder.com/150"
    },
    {
      "id": 10,
      "name": "item10",
      "description": "description10",
      "image": "https://via.placeholder.com/150"
    },
    {
      "id": 11,
      "name": "item11",
      "description": "description11",
      "image": "https://via.placeholder.com/150"
    },
    {
      "id": 12,
      "name": "item12",
      "description": "description12",
      "image": "https://via.placeholder.com/150"
    },
    {
      "id": 13,
      "name": "item13",
      "description": "description13",
      "image": "https://via.placeholder.com/150"
    },
    {
      "id": 14,
      "name": "item14",
      "description": "description14",
      "image": "https://via.placeholder.com/150"
    },
    {
      "id": 15,
      "name": "item15",
      "description": "description15",
      "image": "https://via.placeholder.com/150"
    },
    {
      "id": 16,
      "name": "item16",
      "description": "description16",
      "image": "https://via.placeholder.com/150"
    },
    {
      "id": 17,
      "name": "item17",
      "description": "description17",
      "image": "https://via.placeholder.com/150"
    },
    {
      "id": 18,
      "name": "item18",
      "description": "description18",
      "image": "https://via.placeholder.com/150"
    },
    {
      "id": 19,
      "name": "item19",
      "description": "description19",
      "image": "https://via.placeholder.com/150"
    },
    {
      "id": 20,
      "name": "item20",
      "description": "description20",
      "image": "https://via.placeholder.com/150"
    },
    {
      "id": 21,
      "name": "item21",
      "description": "description21",
      "image": "https://via.placeholder.com/150"
    },
    {
      "id": 22,
      "name": "item22",
      "description": "description22",
      "image": "https://via.placeholder.com/150"
    },
    {
      "id": 23,
      "name": "item23",
      "description": "description23",
      "image": "https://via.placeholder.com/150"
    },
    {
      "id": 24,
      "name": "item24",
      "description": "description24",
      "image": "https://via.placeholder.com/150"
    },
    {
      "id": 25,
      "name": "item25",
      "description": "description25",
      "image": "https://via.placeholder.com/150"
    },
    {
      "id": 26,
      "name": "item26",
      "description": "description26",
      "image": "https://via.placeholder.com/150"
    },
    {
      "id": 27,
      "name": "item27",
      "description": "description27",
      "image": "https://via.placeholder.com/150"
    }
    
  ]
}